proceso/__init__.py
proceso/binding.py
proceso/color.py
proceso/constants.py
proceso/core.py
proceso/data.py
proceso/dom.py
proceso/environment.py
proceso/events.py
proceso/images.py
proceso/io.py
proceso/rendering.py
proceso/shape.py
proceso/structure.py
proceso/sysvars.py
proceso/three_d.py
proceso/transform.py
proceso/typography.py
proceso/utils.py
proceso/math/__init__.py
proceso/math/calculation.py
proceso/math/noise.py
proceso/math/random.py
proceso/math/trigonometry.py
proceso/math/vector.py
proceso-0.0.17.dist-info/LICENSE
proceso-0.0.17.dist-info/METADATA
proceso-0.0.17.dist-info/WHEEL
proceso-0.0.17.dist-info/top_level.txt
proceso-0.0.17.dist-info/RECORD
