Metadata-Version: 2.1
Name: proceso
Version: 0.0.17
Summary: A Python package for creative coding on the web.
Home-page: https://github.com/nickmcintyre/proceso
Author: Nick McIntyre
Author-email: nick@mcintyre.io
Project-URL: Bug Tracker, https://github.com/nickmcintyre/proceso/issues
Classifier: Development Status :: 3 - Alpha
Classifier: License :: OSI Approved :: GNU Lesser General Public License v3 (LGPLv3)
Classifier: Programming Language :: Python :: 3
Classifier: Operating System :: OS Independent
Classifier: Environment :: WebAssembly
Requires-Python: >=3.10
License-File: LICENSE
Requires-Dist: numpy >=1.23
